{
  "type": "Feature",
  "properties": {
    "gn:admin1_code":"1.0",
    "gn:asciiname":"Bambao",
    "gn:cc2":"KM",
    "gn:country_code":"KM",
    "gn:dem":18,
    "gn:feature_class":"P",
    "gn:feature_code":"PPL",
    "gn:name":"Bambao",
    "gn:population":0,
    "gn:timezone":"Indian/Comoro",
    "iso:country":"KM",
    "name:fra_x_preferred":[
        "Bambao Mtrouni"
    ],
    "name:hye_x_preferred":[
        "\u0532\u0561\u0574\u0562\u0561\u0578 \u0544\u057f\u0580\u0578\u0582\u0576\u056b"
    ],
    "name:ind_x_preferred":[
        "Bambao"
    ],
    "name:nld_x_preferred":[
        "Bambao"
    ],
    "name:und_x_variant":[
        "Bambao M\u2019Sanga"
    ],
    "wof:name":"Bambao",
    "wof:placetype":"locality"
},
  "geometry": {"coordinates":[44.51833,-12.19889],"type":"Point"}
}