{
  "type": "Feature",
  "properties": {
    "gn:admin1_code":"1.0",
    "gn:asciiname":"Bambao",
    "gn:cc2":"KM",
    "gn:country_code":"KM",
    "gn:dem":18,
    "gn:feature_class":"P",
    "gn:feature_code":"PPL",
    "gn:name":"Bambao",
    "gn:population":0,
    "gn:timezone":"Indian/Comoro",
    "iso:country":"KM",
    "name:und_x_variant":[
        "Bambao M\u2019Sanga",
        "Bambao"
    ],
    "wof:name":"Bambao",
    "wof:placetype":"locality"
},
  "geometry": {"coordinates":[44.51833,-12.19889],"type":"Point"}
}