{
  "type": "Feature",
  "properties": {
    "gn:admin1_code":"0.0",
    "gn:asciiname":"Malhani",
    "gn:country_code":"KM",
    "gn:dem":268,
    "gn:feature_class":"P",
    "gn:feature_code":"PPL",
    "gn:name":"Malhani",
    "gn:population":0,
    "gn:timezone":"Indian/Comoro",
    "iso:country":"KM",
    "wof:name":"Malhani",
    "wof:placetype":"locality"
},
  "geometry": {"coordinates":[43.78333,-12.35],"type":"Point"}
}