{
  "type": "Feature",
  "properties": {
    "gn:country":"KM",
    "gn:fcode":"PPL",
    "gn:pop":1708,
    "iso:country":"KM",
    "name:bul_x_preferred":[
        "\u041e\u0443\u0441\u0438\u0432\u043e"
    ],
    "name:eng_x_preferred":[
        "Ousivo"
    ],
    "name:nld_x_preferred":[
        "Ousivo"
    ],
    "name:swe_x_preferred":[
        "Oussivo"
    ],
    "name:unk_x_variant":[
        "Ousivo"
    ],
    "qs:name":"Oussivo",
    "qs:photos_9r":0,
    "qs:photos_sr":0,
    "qs:pop_sr":"3",
    "wof:name":"Oussivo",
    "wof:placetype":"locality",
    "wof:population":1708
},
  "geometry": {"coordinates":[43.26722,-11.585],"type":"Point"}
}