{
  "type": "Feature",
  "properties": {
    "gn:admin1_code":"2.0",
    "gn:asciiname":"Ndroini",
    "gn:country_code":"KM",
    "gn:dem":35,
    "gn:feature_class":"P",
    "gn:feature_code":"PPL",
    "gn:name":"Ndroini",
    "gn:population":0,
    "gn:timezone":"Indian/Comoro",
    "iso:country":"KM",
    "wof:name":"Ndroini",
    "wof:placetype":"locality"
},
  "geometry": {"coordinates":[43.24194,-11.76222],"type":"Point"}
}