{
  "type": "Feature",
  "properties": {
    "gn:admin1_code":"2.0",
    "gn:asciiname":"Anihani",
    "gn:country_code":"KM",
    "gn:dem":225,
    "gn:feature_class":"P",
    "gn:feature_code":"PPL",
    "gn:name":"Anihani",
    "gn:population":0,
    "gn:timezone":"Indian/Comoro",
    "iso:country":"KM",
    "wof:name":"Anihani",
    "wof:placetype":"locality"
},
  "geometry": {"coordinates":[43.29528,-11.41083],"type":"Point"}
}