{
  "type": "Feature",
  "properties": {
    "gn:admin1_code":"0.0",
    "gn:asciiname":"Guamarumbo",
    "gn:cc2":"KM",
    "gn:country_code":"KM",
    "gn:dem":5,
    "gn:feature_class":"P",
    "gn:feature_code":"PPL",
    "gn:name":"Guamarumbo",
    "gn:population":0,
    "gn:timezone":"Indian/Comoro",
    "iso:country":"KM",
    "name:und_x_variant":[
        "Guamarombu",
        "Guamarumbo"
    ],
    "wof:name":"Guamarumbo",
    "wof:placetype":"locality"
},
  "geometry": {"coordinates":[43.68333,-12.25],"type":"Point"}
}