{
  "type": "Feature",
  "properties": {
    "gn:country":"KM",
    "gn:fcode":"PPL",
    "gn:population":1698,
    "iso:country":"KM",
    "name:ara_x_preferred":[
        "\u0647\u0627\u0631\u0645\u0628\u0648"
    ],
    "name:arz_x_preferred":[
        "\u0647\u0627\u0631\u0645\u0628\u0648"
    ],
    "name:azb_x_preferred":[
        "\u0647\u0627\u0631\u0645\u0628\u0648"
    ],
    "name:bul_x_preferred":[
        "\u0425\u0430\u0440\u0435\u043c\u0431\u043e"
    ],
    "name:ceb_x_preferred":[
        "Harembo"
    ],
    "name:deu_x_preferred":[
        "Harembo"
    ],
    "name:eng_x_preferred":[
        "Harembo"
    ],
    "name:fas_x_preferred":[
        "\u0647\u0627\u0631\u0645\u0628\u0648"
    ],
    "name:fra_x_preferred":[
        "Harembo"
    ],
    "name:nld_x_preferred":[
        "Harembo"
    ],
    "name:swe_x_preferred":[
        "Harembo"
    ],
    "qs_pg:aaroncc":"KM",
    "qs_pg:gn_country":"KM",
    "qs_pg:gn_fcode":"PPL",
    "qs_pg:gn_pop":1698,
    "qs_pg:name":"Harembo",
    "qs_pg:photos_9r":0,
    "qs_pg:photos_sr":0,
    "qs_pg:pop_sr":3,
    "qs_pg:qs_pg_placetype":"locality",
    "wof:name":"Harembo",
    "wof:placetype":"locality",
    "wof:population":1698
},
  "geometry": {"coordinates":[44.49833,-12.14361],"type":"Point"}
}