{
  "type": "Feature",
  "properties": {
    "gn:country":"KM",
    "gn:fcode":"PPL",
    "gn:pop":426,
    "iso:country":"KM",
    "qs:name":"Midjendj\u00e9ni",
    "qs:photos_9r":0,
    "qs:photos_sr":0,
    "qs:pop_sr":"2",
    "wof:name":"Midjendj\u00e9ni",
    "wof:placetype":"locality",
    "wof:population":426
},
  "geometry": {"coordinates":[43.47611,-11.90917],"type":"Point"}
}