{
  "type": "Feature",
  "properties": {
    "gn:admin1_code":"1.0",
    "gn:asciiname":"Adda-Doueni",
    "gn:country_code":"KM",
    "gn:dem":706,
    "gn:feature_class":"P",
    "gn:feature_code":"PPL",
    "gn:name":"Adda-Dou\u00e9ni",
    "gn:population":10858,
    "gn:timezone":"Indian/Comoro",
    "iso:country":"KM",
    "name:azb_x_preferred":[
        "\u0627\u062f\u0627-\u062f\u0648\u0626\u0646\u06cc"
    ],
    "name:ceb_x_preferred":[
        "Adda-Dou\u00e9ni"
    ],
    "name:fas_x_preferred":[
        "\u0627\u062f\u0627-\u062f\u0648\u0626\u0646\u06cc"
    ],
    "name:fra_x_preferred":[
        "Adda Daou\u00e9ni"
    ],
    "name:hrv_x_preferred":[
        "Adda Daou\u00e9ni"
    ],
    "name:hye_x_preferred":[
        "\u0531\u0564\u0564\u0561-\u0534\u0578\u0582\u0565\u0576\u056b"
    ],
    "name:ind_x_preferred":[
        "Adda-Daou\u00e9ni"
    ],
    "name:ita_x_preferred":[
        "Adda-Dou\u00e9ni"
    ],
    "name:pol_x_preferred":[
        "Adda-Dou\u00e9ni"
    ],
    "name:ron_x_preferred":[
        "Adda Daou\u00e9ni"
    ],
    "name:swe_x_preferred":[
        "Adda-Dou\u00e9ni"
    ],
    "wof:name":"Adda-Doueni",
    "wof:placetype":"locality",
    "wof:population":10858
},
  "geometry": {"coordinates":[44.49722,-12.2925],"type":"Point"}
}