{
  "type": "Feature",
  "properties": {
    "gn:admin1_code":"1.0",
    "gn:asciiname":"Adda-Doueni",
    "gn:country_code":"KM",
    "gn:dem":706,
    "gn:feature_class":"P",
    "gn:feature_code":"PPL",
    "gn:name":"Adda-Dou\u00e9ni",
    "gn:population":10858,
    "gn:timezone":"Indian/Comoro",
    "iso:country":"KM",
    "name:und_x_variant":[
        "Adda-Dou\u00e9ni"
    ],
    "wof:name":"Adda-Doueni",
    "wof:placetype":"locality",
    "wof:population":10858
},
  "geometry": {"coordinates":[44.49722,-12.2925],"type":"Point"}
}