{
  "type": "Feature",
  "properties": {
    "gn:country":"KM",
    "gn:fcode":"PPL",
    "gn:pop":2513,
    "iso:country":"KM",
    "name:bul_x_preferred":[
        "\u0412\u043e\u0443\u0430\u043d\u0438"
    ],
    "name:dut_x_preferred":[
        "Vouani"
    ],
    "name:eng_x_preferred":[
        "Vouani"
    ],
    "name:per_x_preferred":[
        "\u0648\u0648\u0622\u0646\u06cc"
    ],
    "name:swe_x_preferred":[
        "Vouani"
    ],
    "name:unk_x_variant":[
        "Voany"
    ],
    "qs:name":"Vouani",
    "qs:photos_9r":0,
    "qs:photos_sr":0,
    "qs:pop_sr":"4",
    "wd:wordcount":65,
    "wof:name":"Vouani",
    "wof:placetype":"locality",
    "wof:population":2513
},
  "geometry": {"coordinates":[44.37444,-12.24417],"type":"Point"}
}