{
  "type": "Feature",
  "properties": {
    "gn:admin1_code":"0.0",
    "gn:asciiname":"Fongapepo",
    "gn:country_code":"KM",
    "gn:dem":8,
    "gn:feature_class":"P",
    "gn:feature_code":"PPL",
    "gn:name":"Fongapepo",
    "gn:population":0,
    "gn:timezone":"Indian/Comoro",
    "iso:country":"KM",
    "wof:name":"Fongapepo",
    "wof:placetype":"locality"
},
  "geometry": {"coordinates":[43.65,-12.25],"type":"Point"}
}