{
  "type": "Feature",
  "properties": {
    "gn:admin1_code":"1.0",
    "gn:asciiname":"Imere",
    "gn:country_code":"KM",
    "gn:dem":305,
    "gn:feature_class":"P",
    "gn:feature_code":"PPL",
    "gn:name":"Im\u00e9r\u00e9",
    "gn:population":0,
    "gn:timezone":"Indian/Comoro",
    "iso:country":"KM",
    "wof:name":"Imere",
    "wof:placetype":"locality"
},
  "geometry": {"coordinates":[44.36778,-12.23611],"type":"Point"}
}