{
  "type": "Feature",
  "properties": {
    "gn:admin1_code":"2.0",
    "gn:asciiname":"Banda Daoueni",
    "gn:country_code":"KM",
    "gn:dem":450,
    "gn:feature_class":"P",
    "gn:feature_code":"PPL",
    "gn:name":"Banda Daou\u00e9ni",
    "gn:population":0,
    "gn:timezone":"Indian/Comoro",
    "iso:country":"KM",
    "wof:name":"Banda Daoueni",
    "wof:placetype":"locality"
},
  "geometry": {"coordinates":[43.43861,-11.7725],"type":"Point"}
}