{
  "type": "Feature",
  "properties": {
    "gn:admin1_code":"2.0",
    "gn:asciiname":"Salimani",
    "gn:country_code":"KM",
    "gn:dem":40,
    "gn:feature_class":"P",
    "gn:feature_code":"PPL",
    "gn:name":"Salimani",
    "gn:population":0,
    "gn:timezone":"Indian/Comoro",
    "iso:country":"KM",
    "name:ceb_x_preferred":[
        "Salimani"
    ],
    "name:swe_x_preferred":[
        "Salimani"
    ],
    "wof:name":"Salimani",
    "wof:placetype":"locality"
},
  "geometry": {"coordinates":[43.26611,-11.68028],"type":"Point"}
}