{
  "type": "Feature",
  "properties": {
    "gn:admin1_code":"2.0",
    "gn:asciiname":"Dzouadjou",
    "gn:country_code":"KM",
    "gn:dem":507,
    "gn:feature_class":"P",
    "gn:feature_code":"PPL",
    "gn:name":"Dzouadjou",
    "gn:population":0,
    "gn:timezone":"Indian/Comoro",
    "iso:country":"KM",
    "wof:name":"Dzouadjou",
    "wof:placetype":"locality"
},
  "geometry": {"coordinates":[43.42222,-11.87694],"type":"Point"}
}