{
  "type": "Feature",
  "properties": {
    "gn:admin1_code":"2.0",
    "gn:asciiname":"Gouni",
    "gn:country_code":"KM",
    "gn:dem":27,
    "gn:feature_class":"P",
    "gn:feature_code":"PPL",
    "gn:name":"Gouni",
    "gn:population":0,
    "gn:timezone":"Indian/Comoro",
    "iso:country":"KM",
    "wof:name":"Gouni",
    "wof:placetype":"locality"
},
  "geometry": {"coordinates":[43.25667,-11.65361],"type":"Point"}
}