{
  "type": "Feature",
  "properties": {
    "gn:admin1_code":"1.0",
    "gn:asciiname":"Bangouelamvouera",
    "gn:country_code":"KM",
    "gn:dem":79,
    "gn:feature_class":"P",
    "gn:feature_code":"PPL",
    "gn:name":"Bangou\u00e9lamvou\u00e9ra",
    "gn:population":0,
    "gn:timezone":"Indian/Comoro",
    "iso:country":"KM",
    "wof:name":"Bangouelamvouera",
    "wof:placetype":"locality"
},
  "geometry": {"coordinates":[44.22639,-12.17139],"type":"Point"}
}