{
  "type": "Feature",
  "properties": {
    "gn:admin1_code":"2.0",
    "gn:asciiname":"Minassini",
    "gn:country_code":"KM",
    "gn:dem":151,
    "gn:feature_class":"P",
    "gn:feature_code":"PPL",
    "gn:name":"Minassini",
    "gn:population":0,
    "gn:timezone":"Indian/Comoro",
    "iso:country":"KM",
    "wof:name":"Minassini",
    "wof:placetype":"locality"
},
  "geometry": {"coordinates":[43.27333,-11.66278],"type":"Point"}
}