{
  "type": "Feature",
  "properties": {
    "gn:admin1_code":"2.0",
    "gn:asciiname":"Djivani",
    "gn:country_code":"KM",
    "gn:dem":205,
    "gn:feature_class":"P",
    "gn:feature_code":"PPL",
    "gn:name":"Djivani",
    "gn:population":0,
    "gn:timezone":"Indian/Comoro",
    "iso:country":"KM",
    "wof:name":"Djivani",
    "wof:placetype":"locality"
},
  "geometry": {"coordinates":[43.3575,-11.84917],"type":"Point"}
}