{
  "type": "Feature",
  "properties": {
    "gn:admin1_code":"2.0",
    "gn:asciiname":"Mdji Diakagnoa",
    "gn:country_code":"KM",
    "gn:dem":244,
    "gn:feature_class":"P",
    "gn:feature_code":"PPL",
    "gn:name":"Mdji Diakagnoa",
    "gn:population":0,
    "gn:timezone":"Indian/Comoro",
    "iso:country":"KM",
    "wof:name":"Mdji Diakagnoa",
    "wof:placetype":"locality"
},
  "geometry": {"coordinates":[43.40389,-11.87889],"type":"Point"}
}