{
  "type": "Feature",
  "properties": {
    "gn:admin1_code":"0.0",
    "gn:asciiname":"Moujou",
    "gn:country_code":"KM",
    "gn:dem":409,
    "gn:feature_class":"P",
    "gn:feature_code":"PPL",
    "gn:name":"Moujou",
    "gn:population":0,
    "gn:timezone":"Indian/Comoro",
    "iso:country":"KM",
    "wof:name":"Moujou",
    "wof:placetype":"locality"
},
  "geometry": {"coordinates":[44.48333,-12.15],"type":"Point"}
}