{
  "type": "Feature",
  "properties": {
    "gn:country":"KM",
    "gn:fcode":"PPL",
    "gn:population":123,
    "iso:country":"KM",
    "name:eng_x_preferred":[
        "Mbats\u00e9"
    ],
    "name:nld_x_preferred":[
        "Mbats\u00e9"
    ],
    "qs:name":"Mbats\u00e9",
    "qs:photos_9r":0,
    "qs:photos_sr":0,
    "qs:pop_sr":"1",
    "wd:wordcount":32,
    "wof:name":"Mbats\u00e9",
    "wof:placetype":"locality",
    "wof:population":123
},
  "geometry": {"coordinates":[43.39167,-11.45667],"type":"Point"}
}