{
  "type": "Feature",
  "properties": {
    "gn:admin1_code":"2.0",
    "gn:asciiname":"Mirereni",
    "gn:country_code":"KM",
    "gn:dem":68,
    "gn:feature_class":"P",
    "gn:feature_code":"PPL",
    "gn:name":"Mir\u00e9r\u00e9ni",
    "gn:population":0,
    "gn:timezone":"Indian/Comoro",
    "iso:country":"KM",
    "wof:name":"Mirereni",
    "wof:placetype":"locality"
},
  "geometry": {"coordinates":[43.27694,-11.4475],"type":"Point"}
}