{
  "type": "Feature",
  "properties": {
    "gn:admin1_code":"2.0",
    "gn:asciiname":"Boueni",
    "gn:country_code":"KM",
    "gn:dem":569,
    "gn:feature_class":"P",
    "gn:feature_code":"PPL",
    "gn:name":"Bou\u00e9ni",
    "gn:population":0,
    "gn:timezone":"Indian/Comoro",
    "iso:country":"KM",
    "wof:name":"Boueni",
    "wof:placetype":"locality"
},
  "geometry": {"coordinates":[43.3525,-11.63083],"type":"Point"}
}