{
  "type": "Feature",
  "properties": {
    "gn:admin1_code":"2.0",
    "gn:asciiname":"Membeni",
    "gn:country_code":"KM",
    "gn:dem":636,
    "gn:feature_class":"P",
    "gn:feature_code":"PPL",
    "gn:name":"Memb\u00e9ni",
    "gn:population":0,
    "gn:timezone":"Indian/Comoro",
    "iso:country":"KM",
    "wof:name":"Membeni",
    "wof:placetype":"locality"
},
  "geometry": {"coordinates":[43.43306,-11.77389],"type":"Point"}
}