{
  "type": "Feature",
  "properties": {
    "gn:admin1_code":"2.0",
    "gn:asciiname":"Maore",
    "gn:country_code":"KM",
    "gn:dem":285,
    "gn:feature_class":"P",
    "gn:feature_code":"PPL",
    "gn:name":"Maor\u00e9",
    "gn:population":0,
    "gn:timezone":"Indian/Comoro",
    "iso:country":"KM",
    "wof:name":"Maore",
    "wof:placetype":"locality"
},
  "geometry": {"coordinates":[43.38417000000001,-11.42111],"type":"Point"}
}