{
  "type": "Feature",
  "properties": {
    "gn:admin1_code":"1.0",
    "gn:asciiname":"Mromagi",
    "gn:country_code":"KM",
    "gn:dem":65,
    "gn:feature_class":"P",
    "gn:feature_code":"PPL",
    "gn:name":"Mromagi",
    "gn:population":0,
    "gn:timezone":"Indian/Comoro",
    "iso:country":"KM",
    "wof:name":"Mromagi",
    "wof:placetype":"locality"
},
  "geometry": {"coordinates":[44.51056,-12.20361],"type":"Point"}
}