{
  "type": "Feature",
  "properties": {
    "gn:country":"KM",
    "gn:fcode":"PPL",
    "gn:pop":882,
    "iso:country":"KM",
    "name:bul_x_preferred":[
        "\u041c\u0438\u0440\u043e\u043d\u0433\u0430\u043d\u0438"
    ],
    "name:ceb_x_preferred":[
        "Mirongani"
    ],
    "name:eng_x_preferred":[
        "Mirongani"
    ],
    "name:nld_x_preferred":[
        "Mirongani"
    ],
    "name:swe_x_preferred":[
        "Mirongani"
    ],
    "qs:name":"Mirongani",
    "qs:photos_9r":0,
    "qs:photos_sr":0,
    "qs:pop_sr":"2",
    "wd:wordcount":57,
    "wof:name":"Mirongani",
    "wof:placetype":"locality",
    "wof:population":882
},
  "geometry": {"coordinates":[44.2525,-12.19056],"type":"Point"}
}