{
  "type": "Feature",
  "properties": {
    "gn:admin1_code":"2.0",
    "gn:asciiname":"Niadoumboueni",
    "gn:country_code":"KM",
    "gn:dem":653,
    "gn:feature_class":"P",
    "gn:feature_code":"PPL",
    "gn:name":"Niadoumbou\u00e9ni",
    "gn:population":0,
    "gn:timezone":"Indian/Comoro",
    "iso:country":"KM",
    "wof:name":"Niadoumboueni",
    "wof:placetype":"locality"
},
  "geometry": {"coordinates":[43.37667,-11.46778],"type":"Point"}
}