{
  "type": "Feature",
  "properties": {
    "gn:admin1_code":"1.0",
    "gn:asciiname":"Kondroni",
    "gn:cc2":"KM",
    "gn:country_code":"KM",
    "gn:dem":453,
    "gn:feature_class":"P",
    "gn:feature_code":"PPL",
    "gn:name":"Kondroni",
    "gn:population":0,
    "gn:timezone":"Indian/Comoro",
    "iso:country":"KM",
    "name:und_x_variant":[
        "Kondoni",
        "Kondroni"
    ],
    "wof:name":"Kondroni",
    "wof:placetype":"locality"
},
  "geometry": {"coordinates":[44.44722,-12.16861],"type":"Point"}
}