{
  "type": "Feature",
  "properties": {
    "gn:country":"KM",
    "gn:fcode":"PPL",
    "gn:pop":374,
    "iso:country":"KM",
    "qs:name":"Bandamadji",
    "qs:photos_9r":0,
    "qs:photos_sr":0,
    "qs:pop_sr":"2",
    "wof:name":"Bandamadji",
    "wof:placetype":"locality",
    "wof:population":374
},
  "geometry": {"coordinates":[43.38222,-11.41833],"type":"Point"}
}