{
  "type": "Feature",
  "properties": {
    "gn:admin1_code":"2.0",
    "gn:asciiname":"Domoni",
    "gn:country_code":"KM",
    "gn:dem":417,
    "gn:feature_class":"P",
    "gn:feature_code":"PPL",
    "gn:name":"Domoni",
    "gn:population":0,
    "gn:timezone":"Indian/Comoro",
    "iso:country":"KM",
    "name:bre_x_preferred":[
        "Domoni"
    ],
    "name:ceb_x_preferred":[
        "Domoni"
    ],
    "name:deu_x_preferred":[
        "Domoni"
    ],
    "name:fin_x_preferred":[
        "Domoni"
    ],
    "name:fra_x_preferred":[
        "Domoni"
    ],
    "name:hrv_x_preferred":[
        "Domoni"
    ],
    "name:hye_x_preferred":[
        "\u0534\u0578\u0574\u0578\u0576\u056b"
    ],
    "name:ind_x_preferred":[
        "Domoni"
    ],
    "name:ita_x_preferred":[
        "Domoni"
    ],
    "name:lit_x_preferred":[
        "Domonis"
    ],
    "name:nld_x_preferred":[
        "Domoni"
    ],
    "name:pol_x_preferred":[
        "Domoni"
    ],
    "name:por_x_preferred":[
        "Domoni"
    ],
    "name:ron_x_preferred":[
        "Domoni"
    ],
    "name:srp_x_preferred":[
        "\u0414\u043e\u043c\u043e\u043d\u0438"
    ],
    "name:swe_x_preferred":[
        "Domoni"
    ],
    "wof:name":"Domoni",
    "wof:placetype":"locality"
},
  "geometry": {"coordinates":[43.41056,-11.875],"type":"Point"}
}