{
  "type": "Feature",
  "properties": {
    "gn:country":"KM",
    "gn:fcode":"BAY",
    "gn:population":235,
    "iso:country":"KM",
    "qs:name":"Hajanio",
    "qs:photos_9r":0,
    "qs:photos_sr":0,
    "qs:pop_sr":"2",
    "wof:name":"Hajanio",
    "wof:placetype":"locality",
    "wof:population":235
},
  "geometry": {"coordinates":[44.43468,-12.30932],"type":"Point"}
}