{
  "type": "Feature",
  "properties": {
    "gn:country":"KM",
    "gn:fcode":"PPL",
    "gn:pop":2465,
    "iso:country":"KM",
    "name:dut_x_preferred":[
        "Boungoueni"
    ],
    "name:eng_x_preferred":[
        "Boungoueni"
    ],
    "name:fre_x_preferred":[
        "Boungoueni"
    ],
    "name:per_x_preferred":[
        "\u0628\u0648\u0646\u06af\u0648\u0626\u0646\u06cc"
    ],
    "name:swe_x_preferred":[
        "Boungou\u00e9ni"
    ],
    "qs:name":"Boungou\u00e9ni",
    "qs:photos_9r":0,
    "qs:photos_sr":0,
    "qs:pop_sr":"4",
    "wd:wordcount":65,
    "wof:name":"Boungou\u00e9ni",
    "wof:placetype":"locality",
    "wof:population":2465
},
  "geometry": {"coordinates":[44.29944,-12.20556],"type":"Point"}
}