{
  "type": "Feature",
  "properties": {
    "gn:admin1_code":"0.0",
    "gn:asciiname":"Ntsazou",
    "gn:cc2":"KM",
    "gn:country_code":"KM",
    "gn:dem":-9999,
    "gn:feature_class":"P",
    "gn:feature_code":"PPL",
    "gn:name":"Ntsazou",
    "gn:population":0,
    "gn:timezone":"Indian/Comoro",
    "iso:country":"KM",
    "name:und_x_variant":[
        "Sazu",
        "Ntsazou"
    ],
    "wof:name":"Ntsazou",
    "wof:placetype":"locality"
},
  "geometry": {"coordinates":[44.25,-12.16667],"type":"Point"}
}