{
  "type": "Feature",
  "properties": {
    "gn:admin1_code":"0.0",
    "gn:asciiname":"Jiroudain",
    "gn:cc2":"KM",
    "gn:country_code":"KM",
    "gn:dem":131,
    "gn:feature_class":"P",
    "gn:feature_code":"PPL",
    "gn:name":"Jiroudain",
    "gn:population":0,
    "gn:timezone":"Indian/Comoro",
    "iso:country":"KM",
    "name:und_x_variant":[
        "Jiandro",
        "Djiandro",
        "Jiroudain"
    ],
    "wof:name":"Jiroudain",
    "wof:placetype":"locality"
},
  "geometry": {"coordinates":[43.78333,-12.31667],"type":"Point"}
}