{
  "type": "Feature",
  "properties": {
    "gn:admin1_code":"2.0",
    "gn:asciiname":"Mlimani",
    "gn:country_code":"KM",
    "gn:dem":32,
    "gn:feature_class":"P",
    "gn:feature_code":"PPL",
    "gn:name":"Mlimani",
    "gn:population":0,
    "gn:timezone":"Indian/Comoro",
    "iso:country":"KM",
    "wof:name":"Mlimani",
    "wof:placetype":"locality"
},
  "geometry": {"coordinates":[43.39889,-11.88528],"type":"Point"}
}