{
  "type": "Feature",
  "properties": {
    "gn:admin1_code":"2.0",
    "gn:asciiname":"Tsinimouachongo",
    "gn:country_code":"KM",
    "gn:dem":269,
    "gn:feature_class":"P",
    "gn:feature_code":"PPL",
    "gn:name":"Tsinimouachongo",
    "gn:population":0,
    "gn:timezone":"Indian/Comoro",
    "iso:country":"KM",
    "wof:name":"Tsinimouachongo",
    "wof:placetype":"locality"
},
  "geometry": {"coordinates":[43.36611,-11.84556],"type":"Point"}
}