{
  "type": "Feature",
  "properties": {
    "gn:country":"KM",
    "gn:fcode":"PPL",
    "gn:pop":185,
    "iso:country":"KM",
    "qs:name":"Sada",
    "qs:photos_9r":0,
    "qs:photos_sr":0,
    "qs:pop_sr":"1",
    "wd:wordcount":153,
    "wof:name":"Sada",
    "wof:placetype":"locality",
    "wof:population":185
},
  "geometry": {"coordinates":[43.35778,-11.63194],"type":"Point"}
}