{
  "type": "Feature",
  "properties": {
    "gn:admin1_code":"1.0",
    "gn:asciiname":"Mitreni",
    "gn:country_code":"KM",
    "gn:dem":116,
    "gn:feature_class":"P",
    "gn:feature_code":"PPL",
    "gn:name":"Mitr\u00e9ni",
    "gn:population":0,
    "gn:timezone":"Indian/Comoro",
    "iso:country":"KM",
    "name:ceb_x_preferred":[
        "Comuna Mitreni"
    ],
    "name:ita_x_preferred":[
        "Mitreni"
    ],
    "name:msa_x_preferred":[
        "Mitreni"
    ],
    "name:nld_x_preferred":[
        "Mitreni"
    ],
    "name:por_x_preferred":[
        "Mitreni"
    ],
    "name:ron_x_preferred":[
        "Comuna Mitreni"
    ],
    "name:srp_x_preferred":[
        "\u041e\u043f\u0448\u0442\u0438\u043d\u0430 \u041c\u0438\u0442\u0440\u0435\u043d\u0438"
    ],
    "name:ukr_x_preferred":[
        "\u041c\u0456\u0442\u0440\u0435\u043d\u044c"
    ],
    "name:vie_x_preferred":[
        "Mitreni"
    ],
    "name:vol_x_preferred":[
        "Mitreni"
    ],
    "name:zho_x_preferred":[
        "\u7c73\u7279\u96f7\u5c3c\u9109"
    ],
    "wof:name":"Mitreni",
    "wof:placetype":"locality"
},
  "geometry": {"coordinates":[44.31028,-12.22917],"type":"Point"}
}