{
  "type": "Feature",
  "properties": {
    "gn:admin1_code":"1.0",
    "gn:asciiname":"Mitreni",
    "gn:country_code":"KM",
    "gn:dem":116,
    "gn:feature_class":"P",
    "gn:feature_code":"PPL",
    "gn:name":"Mitr\u00e9ni",
    "gn:population":0,
    "gn:timezone":"Indian/Comoro",
    "iso:country":"KM",
    "wof:name":"Mitreni",
    "wof:placetype":"locality"
},
  "geometry": {"coordinates":[44.31028,-12.22917],"type":"Point"}
}