{
  "type": "Feature",
  "properties": {
    "gn:admin1_code":"2.0",
    "gn:asciiname":"Itsangoue",
    "gn:country_code":"KM",
    "gn:dem":544,
    "gn:feature_class":"P",
    "gn:feature_code":"PPL",
    "gn:name":"Itsangou\u00e9",
    "gn:population":0,
    "gn:timezone":"Indian/Comoro",
    "iso:country":"KM",
    "wof:name":"Itsangoue",
    "wof:placetype":"locality"
},
  "geometry": {"coordinates":[43.44278,-11.81028],"type":"Point"}
}