{
  "type": "Feature",
  "properties": {
    "gn:admin1_code":"1.0",
    "gn:asciiname":"Jimilime",
    "gn:country_code":"KM",
    "gn:dem":305,
    "gn:feature_class":"P",
    "gn:feature_code":"PPL",
    "gn:name":"Jimilim\u00e9",
    "gn:population":0,
    "gn:timezone":"Indian/Comoro",
    "iso:country":"KM",
    "name:hye_x_preferred":[
        "\u054b\u056b\u0574\u056b\u056c\u056b\u0574\u0565"
    ],
    "name:ind_x_preferred":[
        "Jimilim\u00e9"
    ],
    "name:und_x_variant":[
        "Jimilim\u00e9"
    ],
    "wof:name":"Jimilime",
    "wof:placetype":"locality"
},
  "geometry": {"coordinates":[44.46361,-12.09361],"type":"Point"}
}