{
  "type": "Feature",
  "properties": {
    "gn:admin1_code":"2.0",
    "gn:asciiname":"Bangoua",
    "gn:country_code":"KM",
    "gn:dem":50,
    "gn:feature_class":"P",
    "gn:feature_code":"PPL",
    "gn:name":"Bangoua",
    "gn:population":0,
    "gn:timezone":"Indian/Comoro",
    "iso:country":"KM",
    "wof:name":"Bangoua",
    "wof:placetype":"locality"
},
  "geometry": {"coordinates":[43.27806,-11.84028],"type":"Point"}
}